{
  "active": "Vanilla",
  "profiles": {
    "Vanilla": {
      "name": "Vanilla",
      "server_path": "D:\\MINECRAFT_SERVER_TEST",
      "server_ip": "localhost",
      "run_script": "run.bat",
      "rcon_password": "CoMO4ghnD_J4keB-mbe2ZQ",
      "rcon_port": 27001,
      "query_port": 27002,
      "auth_key": "",
      "shutdown_key": "",
      "inactivity_limit": 1800,
      "polling_interval": 60,
      "pc_sleep_after_inactivity": true,
      "description": "",
      "env_scope": "per_server"
    },
    "test": {
      "name": "test",
      "server_path": "D:\\MINECRAFT_SERVER_TEST",
      "server_ip": "localhost",
      "run_script": "run.bat",
      "rcon_password": "nVTFhWRwDf8drhRip379KQ",
      "rcon_port": 27001,
      "query_port": 27002,
      "auth_key": "",
      "shutdown_key": "",
      "inactivity_limit": 120,
      "polling_interval": 60,
      "pc_sleep_after_inactivity": true,
      "description": "",
      "env_scope": "per_server"
    }
  }
}